LICENSE
MANIFEST.in
README.md
requirements.txt
setup.py
hapapi/__init__.py
hapapi/__main__.py
hapapi.egg-info/PKG-INFO
hapapi.egg-info/SOURCES.txt
hapapi.egg-info/dependency_links.txt
hapapi.egg-info/entry_points.txt
hapapi.egg-info/requires.txt
hapapi.egg-info/top_level.txt
hapapi/api/__init__.py
hapapi/api/auth.py
hapapi/api/backend.py
hapapi/api/mixins.py
hapapi/api/proxy.py
hapapi/api/root.py
hapapi/haproxy/__init__.py